{
  "books": [
    {
      "id": "Genesis",
      "order": 1,
      "name_en": "Genesis",
      "name_ko": "창세기"
    },
    {
      "id": "Exodus",
      "order": 2,
      "name_en": "Exodus",
      "name_ko": "출애굽기"
    },
    {
      "id": "Leviticus",
      "order": 3,
      "name_en": "Leviticus",
      "name_ko": "레위기"
    },
    {
      "id": "Numbers",
      "order": 4,
      "name_en": "Numbers",
      "name_ko": "민수기"
    },
    {
      "id": "Deuteronomy",
      "order": 5,
      "name_en": "Deuteronomy",
      "name_ko": "신명기"
    },
    {
      "id": "Joshua",
      "order": 6,
      "name_en": "Joshua",
      "name_ko": "여호수아"
    },
    {
      "id": "Judges",
      "order": 7,
      "name_en": "Judges",
      "name_ko": "사사기"
    },
    {
      "id": "Ruth",
      "order": 8,
      "name_en": "Ruth",
      "name_ko": "룻기"
    },
    {
      "id": "1 Samuel",
      "order": 9,
      "name_en": "1 Samuel",
      "name_ko": "사무엘상"
    },
    {
      "id": "2 Samuel",
      "order": 10,
      "name_en": "2 Samuel",
      "name_ko": "사무엘하"
    },
    {
      "id": "1 Kings",
      "order": 11,
      "name_en": "1 Kings",
      "name_ko": "열왕기상"
    },
    {
      "id": "2 Kings",
      "order": 12,
      "name_en": "2 Kings",
      "name_ko": "열왕기하"
    },
    {
      "id": "1 Chronicles",
      "order": 13,
      "name_en": "1 Chronicles",
      "name_ko": "역대상"
    },
    {
      "id": "2 Chronicles",
      "order": 14,
      "name_en": "2 Chronicles",
      "name_ko": "역대하"
    },
    {
      "id": "Ezra",
      "order": 15,
      "name_en": "Ezra",
      "name_ko": "에스라"
    },
    {
      "id": "Nehemiah",
      "order": 16,
      "name_en": "Nehemiah",
      "name_ko": "느헤미야"
    },
    {
      "id": "Esther",
      "order": 17,
      "name_en": "Esther",
      "name_ko": "에스더"
    },
    {
      "id": "Job",
      "order": 18,
      "name_en": "Job",
      "name_ko": "욥기"
    },
    {
      "id": "Psalms",
      "order": 19,
      "name_en": "Psalms",
      "name_ko": "시편"
    },
    {
      "id": "Proverbs",
      "order": 20,
      "name_en": "Proverbs",
      "name_ko": "잠언"
    },
    {
      "id": "Ecclesiastes",
      "order": 21,
      "name_en": "Ecclesiastes",
      "name_ko": "전도서"
    },
    {
      "id": "Song of Solomon",
      "order": 22,
      "name_en": "Song of Solomon",
      "name_ko": "아가"
    },
    {
      "id": "Isaiah",
      "order": 23,
      "name_en": "Isaiah",
      "name_ko": "이사야"
    },
    {
      "id": "Jeremiah",
      "order": 24,
      "name_en": "Jeremiah",
      "name_ko": "예레미야"
    },
    {
      "id": "Lamentations",
      "order": 25,
      "name_en": "Lamentations",
      "name_ko": "예레미야애가"
    },
    {
      "id": "Ezekiel",
      "order": 26,
      "name_en": "Ezekiel",
      "name_ko": "에스겔"
    },
    {
      "id": "Daniel",
      "order": 27,
      "name_en": "Daniel",
      "name_ko": "다니엘"
    },
    {
      "id": "Hosea",
      "order": 28,
      "name_en": "Hosea",
      "name_ko": "호세아"
    },
    {
      "id": "Joel",
      "order": 29,
      "name_en": "Joel",
      "name_ko": "요엘"
    },
    {
      "id": "Amos",
      "order": 30,
      "name_en": "Amos",
      "name_ko": "아모스"
    },
    {
      "id": "Obadiah",
      "order": 31,
      "name_en": "Obadiah",
      "name_ko": "오바댜"
    },
    {
      "id": "Jonah",
      "order": 32,
      "name_en": "Jonah",
      "name_ko": "요나"
    },
    {
      "id": "Micah",
      "order": 33,
      "name_en": "Micah",
      "name_ko": "미가"
    },
    {
      "id": "Nahum",
      "order": 34,
      "name_en": "Nahum",
      "name_ko": "나훔"
    },
    {
      "id": "Habakkuk",
      "order": 35,
      "name_en": "Habakkuk",
      "name_ko": "하박국"
    },
    {
      "id": "Zephaniah",
      "order": 36,
      "name_en": "Zephaniah",
      "name_ko": "스바냐"
    },
    {
      "id": "Haggai",
      "order": 37,
      "name_en": "Haggai",
      "name_ko": "학개"
    },
    {
      "id": "Zechariah",
      "order": 38,
      "name_en": "Zechariah",
      "name_ko": "스가랴"
    },
    {
      "id": "Malachi",
      "order": 39,
      "name_en": "Malachi",
      "name_ko": "말라기"
    }
  ],
  "translations": {
    "BHS": {
      "label": "BHS",
      "language": "he",
      "dir": "역본/BHS",
      "direction": "rtl",
      "bookDirs": {
        "Genesis": "01 Genesis",
        "Exodus": "02 Exodus",
        "Leviticus": "03 Leviticus",
        "Numbers": "04 Numbers",
        "Deuteronomy": "05 Deuteronomy",
        "Joshua": "06 Joshua",
        "Judges": "07 Judges",
        "Ruth": "08 Ruth",
        "1 Samuel": "09 1 Samuel",
        "2 Samuel": "10 2 Samuel",
        "1 Kings": "11 1 Kings",
        "2 Kings": "12 2 Kings",
        "1 Chronicles": "13 1 Chronicles",
        "2 Chronicles": "14 2 Chronicles",
        "Ezra": "15 Ezra",
        "Nehemiah": "16 Nehemiah",
        "Esther": "17 Esther",
        "Job": "18 Job",
        "Psalms": "19 Psalms",
        "Proverbs": "20 Proverbs",
        "Ecclesiastes": "21 Ecclesiastes",
        "Song of Solomon": "22 Song of Solomon",
        "Isaiah": "23 Isaiah",
        "Jeremiah": "24 Jeremiah",
        "Lamentations": "25 Lamentations",
        "Ezekiel": "26 Ezekiel",
        "Daniel": "27 Daniel",
        "Hosea": "28 Hosea",
        "Joel": "29 Joel",
        "Amos": "30 Amos",
        "Obadiah": "31 Obadiah",
        "Jonah": "32 Jonah",
        "Micah": "33 Micah",
        "Nahum": "34 Nahum",
        "Habakkuk": "35 Habakkuk",
        "Zephaniah": "36 Zephaniah",
        "Haggai": "37 Haggai",
        "Zechariah": "38 Zechariah",
        "Malachi": "39 Malachi"
      },
      "chapterFiles": {
        "Genesis": [
          "01.md",
          "02.md",
          "03.md",
          "04.md",
          "05.md",
          "06.md",
          "07.md",
          "08.md",
          "09.md",
          "10.md",
          "11.md",
          "12.md",
          "13.md",
          "14.md",
          "15.md",
          "16.md",
          "17.md",
          "18.md",
          "19.md",
          "20.md",
          "21.md",
          "22.md",
          "23.md",
          "24.md",
          "25.md",
          "26.md",
          "27.md",
          "28.md",
          "29.md",
          "30.md",
          "31.md",
          "32.md",
          "33.md",
          "34.md",
          "35.md",
          "36.md",
          "37.md",
          "38.md",
          "39.md",
          "40.md",
          "41.md",
          "42.md",
          "43.md",
          "44.md",
          "45.md",
          "46.md",
          "47.md",
          "48.md",
          "49.md",
          "50.md"
        ],
        "Exodus": [
          "01.md",
          "02.md",
          "03.md",
          "04.md",
          "05.md",
          "06.md",
          "07.md",
          "08.md",
          "09.md",
          "10.md",
          "11.md",
          "12.md",
          "13.md",
          "14.md",
          "15.md",
          "16.md",
          "17.md",
          "18.md",
          "19.md",
          "20.md",
          "21.md",
          "22.md",
          "23.md",
          "24.md",
          "25.md",
          "26.md",
          "27.md",
          "28.md",
          "29.md",
          "30.md",
          "31.md",
          "32.md",
          "33.md",
          "34.md",
          "35.md",
          "36.md",
          "37.md",
          "38.md",
          "39.md",
          "40.md"
        ],
        "Leviticus": [
          "01.md",
          "02.md",
          "03.md",
          "04.md",
          "05.md",
          "06.md",
          "07.md",
          "08.md",
          "09.md",
          "10.md",
          "11.md",
          "12.md",
          "13.md",
          "14.md",
          "15.md",
          "16.md",
          "17.md",
          "18.md",
          "19.md",
          "20.md",
          "21.md",
          "22.md",
          "23.md",
          "24.md",
          "25.md",
          "26.md",
          "27.md"
        ],
        "Numbers": [
          "01.md",
          "02.md",
          "03.md",
          "04.md",
          "05.md",
          "06.md",
          "07.md",
          "08.md",
          "09.md",
          "10.md",
          "11.md",
          "12.md",
          "13.md",
          "14.md",
          "15.md",
          "16.md",
          "17.md",
          "18.md",
          "19.md",
          "20.md",
          "21.md",
          "22.md",
          "23.md",
          "24.md",
          "25.md",
          "26.md",
          "27.md",
          "28.md",
          "29.md",
          "30.md",
          "31.md",
          "32.md",
          "33.md",
          "34.md",
          "35.md",
          "36.md"
        ],
        "Deuteronomy": [
          "01.md",
          "02.md",
          "03.md",
          "04.md",
          "05.md",
          "06.md",
          "07.md",
          "08.md",
          "09.md",
          "10.md",
          "11.md",
          "12.md",
          "13.md",
          "14.md",
          "15.md",
          "16.md",
          "17.md",
          "18.md",
          "19.md",
          "20.md",
          "21.md",
          "22.md",
          "23.md",
          "24.md",
          "25.md",
          "26.md",
          "27.md",
          "28.md",
          "29.md",
          "30.md",
          "31.md",
          "32.md",
          "33.md",
          "34.md"
        ],
        "Joshua": [
          "01.md",
          "02.md",
          "03.md",
          "04.md",
          "05.md",
          "06.md",
          "07.md",
          "08.md",
          "09.md",
          "10.md",
          "11.md",
          "12.md",
          "13.md",
          "14.md",
          "15.md",
          "16.md",
          "17.md",
          "18.md",
          "19.md",
          "20.md",
          "21.md",
          "22.md",
          "23.md",
          "24.md"
        ],
        "Judges": [
          "01.md",
          "02.md",
          "03.md",
          "04.md",
          "05.md",
          "06.md",
          "07.md",
          "08.md",
          "09.md",
          "10.md",
          "11.md",
          "12.md",
          "13.md",
          "14.md",
          "15.md",
          "16.md",
          "17.md",
          "18.md",
          "19.md",
          "20.md",
          "21.md"
        ],
        "Ruth": [
          "01.md",
          "02.md",
          "03.md",
          "04.md"
        ],
        "1 Samuel": [
          "01.md",
          "02.md",
          "03.md",
          "04.md",
          "05.md",
          "06.md",
          "07.md",
          "08.md",
          "09.md",
          "10.md",
          "11.md",
          "12.md",
          "13.md",
          "14.md",
          "15.md",
          "16.md",
          "17.md",
          "18.md",
          "19.md",
          "20.md",
          "21.md",
          "22.md",
          "23.md",
          "24.md",
          "25.md",
          "26.md",
          "27.md",
          "28.md",
          "29.md",
          "30.md",
          "31.md"
        ],
        "2 Samuel": [
          "01.md",
          "02.md",
          "03.md",
          "04.md",
          "05.md",
          "06.md",
          "07.md",
          "08.md",
          "09.md",
          "10.md",
          "11.md",
          "12.md",
          "13.md",
          "14.md",
          "15.md",
          "16.md",
          "17.md",
          "18.md",
          "19.md",
          "20.md",
          "21.md",
          "22.md",
          "23.md",
          "24.md"
        ],
        "1 Kings": [
          "01.md",
          "02.md",
          "03.md",
          "04.md",
          "05.md",
          "06.md",
          "07.md",
          "08.md",
          "09.md",
          "10.md",
          "11.md",
          "12.md",
          "13.md",
          "14.md",
          "15.md",
          "16.md",
          "17.md",
          "18.md",
          "19.md",
          "20.md",
          "21.md",
          "22.md"
        ],
        "2 Kings": [
          "01.md",
          "02.md",
          "03.md",
          "04.md",
          "05.md",
          "06.md",
          "07.md",
          "08.md",
          "09.md",
          "10.md",
          "11.md",
          "12.md",
          "13.md",
          "14.md",
          "15.md",
          "16.md",
          "17.md",
          "18.md",
          "19.md",
          "20.md",
          "21.md",
          "22.md",
          "23.md",
          "24.md",
          "25.md"
        ],
        "1 Chronicles": [
          "01.md",
          "02.md",
          "03.md",
          "04.md",
          "05.md",
          "06.md",
          "07.md",
          "08.md",
          "09.md",
          "10.md",
          "11.md",
          "12.md",
          "13.md",
          "14.md",
          "15.md",
          "16.md",
          "17.md",
          "18.md",
          "19.md",
          "20.md",
          "21.md",
          "22.md",
          "23.md",
          "24.md",
          "25.md",
          "26.md",
          "27.md",
          "28.md",
          "29.md"
        ],
        "2 Chronicles": [
          "01.md",
          "02.md",
          "03.md",
          "04.md",
          "05.md",
          "06.md",
          "07.md",
          "08.md",
          "09.md",
          "10.md",
          "11.md",
          "12.md",
          "13.md",
          "14.md",
          "15.md",
          "16.md",
          "17.md",
          "18.md",
          "19.md",
          "20.md",
          "21.md",
          "22.md",
          "23.md",
          "24.md",
          "25.md",
          "26.md",
          "27.md",
          "28.md",
          "29.md",
          "30.md",
          "31.md",
          "32.md",
          "33.md",
          "34.md",
          "35.md",
          "36.md"
        ],
        "Ezra": [
          "01.md",
          "02.md",
          "03.md",
          "04.md",
          "05.md",
          "06.md",
          "07.md",
          "08.md",
          "09.md",
          "10.md"
        ],
        "Nehemiah": [
          "01.md",
          "02.md",
          "03.md",
          "04.md",
          "05.md",
          "06.md",
          "07.md",
          "08.md",
          "09.md",
          "10.md",
          "11.md",
          "12.md",
          "13.md"
        ],
        "Esther": [
          "01.md",
          "02.md",
          "03.md",
          "04.md",
          "05.md",
          "06.md",
          "07.md",
          "08.md",
          "09.md",
          "10.md"
        ],
        "Job": [
          "01.md",
          "02.md",
          "03.md",
          "04.md",
          "05.md",
          "06.md",
          "07.md",
          "08.md",
          "09.md",
          "10.md",
          "11.md",
          "12.md",
          "13.md",
          "14.md",
          "15.md",
          "16.md",
          "17.md",
          "18.md",
          "19.md",
          "20.md",
          "21.md",
          "22.md",
          "23.md",
          "24.md",
          "25.md",
          "26.md",
          "27.md",
          "28.md",
          "29.md",
          "30.md",
          "31.md",
          "32.md",
          "33.md",
          "34.md",
          "35.md",
          "36.md",
          "37.md",
          "38.md",
          "39.md",
          "40.md",
          "41.md",
          "42.md"
        ],
        "Psalms": [
          "001.md",
          "002.md",
          "003.md",
          "004.md",
          "005.md",
          "006.md",
          "007.md",
          "008.md",
          "009.md",
          "010.md",
          "011.md",
          "012.md",
          "013.md",
          "014.md",
          "015.md",
          "016.md",
          "017.md",
          "018.md",
          "019.md",
          "020.md",
          "021.md",
          "022.md",
          "023.md",
          "024.md",
          "025.md",
          "026.md",
          "027.md",
          "028.md",
          "029.md",
          "030.md",
          "031.md",
          "032.md",
          "033.md",
          "034.md",
          "035.md",
          "036.md",
          "037.md",
          "038.md",
          "039.md",
          "040.md",
          "041.md",
          "042.md",
          "043.md",
          "044.md",
          "045.md",
          "046.md",
          "047.md",
          "048.md",
          "049.md",
          "050.md",
          "051.md",
          "052.md",
          "053.md",
          "054.md",
          "055.md",
          "056.md",
          "057.md",
          "058.md",
          "059.md",
          "060.md",
          "061.md",
          "062.md",
          "063.md",
          "064.md",
          "065.md",
          "066.md",
          "067.md",
          "068.md",
          "069.md",
          "070.md",
          "071.md",
          "072.md",
          "073.md",
          "074.md",
          "075.md",
          "076.md",
          "077.md",
          "078.md",
          "079.md",
          "080.md",
          "081.md",
          "082.md",
          "083.md",
          "084.md",
          "085.md",
          "086.md",
          "087.md",
          "088.md",
          "089.md",
          "090.md",
          "091.md",
          "092.md",
          "093.md",
          "094.md",
          "095.md",
          "096.md",
          "097.md",
          "098.md",
          "099.md",
          "100.md",
          "101.md",
          "102.md",
          "103.md",
          "104.md",
          "105.md",
          "106.md",
          "107.md",
          "108.md",
          "109.md",
          "110.md",
          "111.md",
          "112.md",
          "113.md",
          "114.md",
          "115.md",
          "116.md",
          "117.md",
          "118.md",
          "119.md",
          "120.md",
          "121.md",
          "122.md",
          "123.md",
          "124.md",
          "125.md",
          "126.md",
          "127.md",
          "128.md",
          "129.md",
          "130.md",
          "131.md",
          "132.md",
          "133.md",
          "134.md",
          "135.md",
          "136.md",
          "137.md",
          "138.md",
          "139.md",
          "140.md",
          "141.md",
          "142.md",
          "143.md",
          "144.md",
          "145.md",
          "146.md",
          "147.md",
          "148.md",
          "149.md",
          "150.md"
        ],
        "Proverbs": [
          "01.md",
          "02.md",
          "03.md",
          "04.md",
          "05.md",
          "06.md",
          "07.md",
          "08.md",
          "09.md",
          "10.md",
          "11.md",
          "12.md",
          "13.md",
          "14.md",
          "15.md",
          "16.md",
          "17.md",
          "18.md",
          "19.md",
          "20.md",
          "21.md",
          "22.md",
          "23.md",
          "24.md",
          "25.md",
          "26.md",
          "27.md",
          "28.md",
          "29.md",
          "30.md",
          "31.md"
        ],
        "Ecclesiastes": [
          "01.md",
          "02.md",
          "03.md",
          "04.md",
          "05.md",
          "06.md",
          "07.md",
          "08.md",
          "09.md",
          "10.md",
          "11.md",
          "12.md"
        ],
        "Song of Solomon": [
          "01.md",
          "02.md",
          "03.md",
          "04.md",
          "05.md",
          "06.md",
          "07.md",
          "08.md"
        ],
        "Isaiah": [
          "01.md",
          "02.md",
          "03.md",
          "04.md",
          "05.md",
          "06.md",
          "07.md",
          "08.md",
          "09.md",
          "10.md",
          "11.md",
          "12.md",
          "13.md",
          "14.md",
          "15.md",
          "16.md",
          "17.md",
          "18.md",
          "19.md",
          "20.md",
          "21.md",
          "22.md",
          "23.md",
          "24.md",
          "25.md",
          "26.md",
          "27.md",
          "28.md",
          "29.md",
          "30.md",
          "31.md",
          "32.md",
          "33.md",
          "34.md",
          "35.md",
          "36.md",
          "37.md",
          "38.md",
          "39.md",
          "40.md",
          "41.md",
          "42.md",
          "43.md",
          "44.md",
          "45.md",
          "46.md",
          "47.md",
          "48.md",
          "49.md",
          "50.md",
          "51.md",
          "52.md",
          "53.md",
          "54.md",
          "55.md",
          "56.md",
          "57.md",
          "58.md",
          "59.md",
          "60.md",
          "61.md",
          "62.md",
          "63.md",
          "64.md",
          "65.md",
          "66.md"
        ],
        "Jeremiah": [
          "01.md",
          "02.md",
          "03.md",
          "04.md",
          "05.md",
          "06.md",
          "07.md",
          "08.md",
          "09.md",
          "10.md",
          "11.md",
          "12.md",
          "13.md",
          "14.md",
          "15.md",
          "16.md",
          "17.md",
          "18.md",
          "19.md",
          "20.md",
          "21.md",
          "22.md",
          "23.md",
          "24.md",
          "25.md",
          "26.md",
          "27.md",
          "28.md",
          "29.md",
          "30.md",
          "31.md",
          "32.md",
          "33.md",
          "34.md",
          "35.md",
          "36.md",
          "37.md",
          "38.md",
          "39.md",
          "40.md",
          "41.md",
          "42.md",
          "43.md",
          "44.md",
          "45.md",
          "46.md",
          "47.md",
          "48.md",
          "49.md",
          "50.md",
          "51.md",
          "52.md"
        ],
        "Lamentations": [
          "01.md",
          "02.md",
          "03.md",
          "04.md",
          "05.md"
        ],
        "Ezekiel": [
          "01.md",
          "02.md",
          "03.md",
          "04.md",
          "05.md",
          "06.md",
          "07.md",
          "08.md",
          "09.md",
          "10.md",
          "11.md",
          "12.md",
          "13.md",
          "14.md",
          "15.md",
          "16.md",
          "17.md",
          "18.md",
          "19.md",
          "20.md",
          "21.md",
          "22.md",
          "23.md",
          "24.md",
          "25.md",
          "26.md",
          "27.md",
          "28.md",
          "29.md",
          "30.md",
          "31.md",
          "32.md",
          "33.md",
          "34.md",
          "35.md",
          "36.md",
          "37.md",
          "38.md",
          "39.md",
          "40.md",
          "41.md",
          "42.md",
          "43.md",
          "44.md",
          "45.md",
          "46.md",
          "47.md",
          "48.md"
        ],
        "Daniel": [
          "01.md",
          "02.md",
          "03.md",
          "04.md",
          "05.md",
          "06.md",
          "07.md",
          "08.md",
          "09.md",
          "10.md",
          "11.md",
          "12.md"
        ],
        "Hosea": [
          "01.md",
          "02.md",
          "03.md",
          "04.md",
          "05.md",
          "06.md",
          "07.md",
          "08.md",
          "09.md",
          "10.md",
          "11.md",
          "12.md",
          "13.md",
          "14.md"
        ],
        "Joel": [
          "01.md",
          "02.md",
          "03.md",
          "04.md"
        ],
        "Amos": [
          "01.md",
          "02.md",
          "03.md",
          "04.md",
          "05.md",
          "06.md",
          "07.md",
          "08.md",
          "09.md"
        ],
        "Obadiah": [
          "01.md"
        ],
        "Jonah": [
          "01.md",
          "02.md",
          "03.md",
          "04.md"
        ],
        "Micah": [
          "01.md",
          "02.md",
          "03.md",
          "04.md",
          "05.md",
          "06.md",
          "07.md"
        ],
        "Nahum": [
          "01.md",
          "02.md",
          "03.md"
        ],
        "Habakkuk": [
          "01.md",
          "02.md",
          "03.md"
        ],
        "Zephaniah": [
          "01.md",
          "02.md",
          "03.md"
        ],
        "Haggai": [
          "01.md",
          "02.md"
        ],
        "Zechariah": [
          "01.md",
          "02.md",
          "03.md",
          "04.md",
          "05.md",
          "06.md",
          "07.md",
          "08.md",
          "09.md",
          "10.md",
          "11.md",
          "12.md",
          "13.md",
          "14.md"
        ],
        "Malachi": [
          "01.md",
          "02.md",
          "03.md"
        ]
      }
    },
    "KNT": {
      "label": "KNT (새한글성경 정리)",
      "language": "ko",
      "dir": "역본/KNT",
      "direction": "ltr",
      "bookDirs": {
        "Nahum": "나훔",
        "Nehemiah": "느헤미야",
        "Daniel": "다니엘",
        "Leviticus": "레위기",
        "Ruth": "룻기",
        "Malachi": "말라기",
        "Micah": "미가",
        "Numbers": "민수기",
        "1 Samuel": "사무엘상",
        "2 Samuel": "사무엘하",
        "Judges": "사사기",
        "Zechariah": "스가랴",
        "Zephaniah": "스바냐",
        "Psalms": "시편",
        "Deuteronomy": "신명기",
        "Song of Solomon": "아가",
        "Amos": "아모스",
        "Ezekiel": "에스겔",
        "Esther": "에스더",
        "Ezra": "에스라",
        "Joshua": "여호수아",
        "1 Chronicles": "역대상",
        "2 Chronicles": "역대하",
        "1 Kings": "열왕기상",
        "2 Kings": "열왕기하",
        "Jeremiah": "예레미야",
        "Lamentations": "예레미야애가",
        "Obadiah": "오바댜",
        "Jonah": "요나",
        "Joel": "요엘",
        "Job": "욥기",
        "Isaiah": "이사야",
        "Proverbs": "잠언",
        "Ecclesiastes": "전도서",
        "Genesis": "창세기",
        "Exodus": "출애굽기",
        "Habakkuk": "하박국",
        "Haggai": "학개",
        "Hosea": "호세아"
      },
      "chapterFiles": {
        "Nahum": [
          "01.md",
          "02.md",
          "03.md"
        ],
        "Nehemiah": [
          "01.md",
          "02.md",
          "03.md",
          "04.md",
          "05.md",
          "06.md",
          "07.md",
          "08.md",
          "09.md",
          "10.md",
          "11.md",
          "12.md",
          "13.md"
        ],
        "Daniel": [
          "01.md",
          "02.md",
          "03.md",
          "04.md",
          "05.md",
          "06.md",
          "07.md",
          "08.md",
          "09.md",
          "10.md",
          "11.md",
          "12.md"
        ],
        "Leviticus": [
          "01.md",
          "02.md",
          "03.md",
          "04.md",
          "05.md",
          "06.md",
          "07.md",
          "08.md",
          "09.md",
          "10.md",
          "11.md",
          "12.md",
          "13.md",
          "14.md",
          "15.md",
          "16.md",
          "17.md",
          "18.md",
          "19.md",
          "20.md",
          "21.md",
          "22.md",
          "23.md",
          "24.md",
          "25.md",
          "26.md",
          "27.md"
        ],
        "Ruth": [
          "01.md",
          "02.md",
          "03.md",
          "04.md"
        ],
        "Malachi": [
          "01.md",
          "02.md",
          "03.md",
          "04.md"
        ],
        "Micah": [
          "01.md",
          "02.md",
          "03.md",
          "04.md",
          "05.md",
          "06.md",
          "07.md"
        ],
        "Numbers": [
          "01.md",
          "02.md",
          "03.md",
          "04.md",
          "05.md",
          "06.md",
          "07.md",
          "08.md",
          "09.md",
          "10.md",
          "11.md",
          "12.md",
          "13.md",
          "14.md",
          "15.md",
          "16.md",
          "17.md",
          "18.md",
          "19.md",
          "20.md",
          "21.md",
          "22.md",
          "23.md",
          "24.md",
          "25.md",
          "26.md",
          "27.md",
          "28.md",
          "29.md",
          "30.md",
          "31.md",
          "32.md",
          "33.md",
          "34.md",
          "35.md",
          "36.md"
        ],
        "1 Samuel": [
          "01.md",
          "02.md",
          "03.md",
          "04.md",
          "05.md",
          "06.md",
          "07.md",
          "08.md",
          "09.md",
          "10.md",
          "11.md",
          "12.md",
          "13.md",
          "14.md",
          "15.md",
          "16.md",
          "17.md",
          "18.md",
          "19.md",
          "20.md",
          "21.md",
          "22.md",
          "23.md",
          "24.md",
          "25.md",
          "26.md",
          "27.md",
          "28.md",
          "29.md",
          "30.md",
          "31.md"
        ],
        "2 Samuel": [
          "01.md",
          "02.md",
          "03.md",
          "04.md",
          "05.md",
          "06.md",
          "07.md",
          "08.md",
          "09.md",
          "10.md",
          "11.md",
          "12.md",
          "13.md",
          "14.md",
          "15.md",
          "16.md",
          "17.md",
          "18.md",
          "19.md",
          "20.md",
          "21.md",
          "22.md",
          "23.md",
          "24.md"
        ],
        "Judges": [
          "01.md",
          "02.md",
          "03.md",
          "04.md",
          "05.md",
          "06.md",
          "07.md",
          "08.md",
          "09.md",
          "10.md",
          "11.md",
          "12.md",
          "13.md",
          "14.md",
          "15.md",
          "16.md",
          "17.md",
          "18.md",
          "19.md",
          "20.md",
          "21.md"
        ],
        "Zechariah": [
          "01.md",
          "02.md",
          "03.md",
          "04.md",
          "05.md",
          "06.md",
          "07.md",
          "08.md",
          "09.md",
          "10.md",
          "11.md",
          "12.md",
          "13.md",
          "14.md"
        ],
        "Zephaniah": [
          "01.md",
          "02.md",
          "03.md"
        ],
        "Psalms": [
          "01.md",
          "02.md",
          "03.md",
          "04.md",
          "05.md",
          "06.md",
          "07.md",
          "08.md",
          "09.md",
          "10.md",
          "11.md",
          "12.md",
          "13.md",
          "14.md",
          "15.md",
          "16.md",
          "17.md",
          "18.md",
          "19.md",
          "20.md",
          "21.md",
          "22.md",
          "23.md",
          "24.md",
          "25.md",
          "26.md",
          "27.md",
          "28.md",
          "29.md",
          "30.md",
          "31.md",
          "32.md",
          "33.md",
          "34.md",
          "35.md",
          "36.md",
          "37.md",
          "38.md",
          "39.md",
          "40.md",
          "41.md",
          "42.md",
          "43.md",
          "44.md",
          "45.md",
          "46.md",
          "47.md",
          "48.md",
          "49.md",
          "50.md",
          "51.md",
          "52.md",
          "53.md",
          "54.md",
          "55.md",
          "56.md",
          "57.md",
          "58.md",
          "59.md",
          "60.md",
          "61.md",
          "62.md",
          "63.md",
          "64.md",
          "65.md",
          "66.md",
          "67.md",
          "68.md",
          "69.md",
          "70.md",
          "71.md",
          "72.md",
          "73.md",
          "74.md",
          "75.md",
          "76.md",
          "77.md",
          "78.md",
          "79.md",
          "80.md",
          "81.md",
          "82.md",
          "83.md",
          "84.md",
          "85.md",
          "86.md",
          "87.md",
          "88.md",
          "89.md",
          "90.md",
          "91.md",
          "92.md",
          "93.md",
          "94.md",
          "95.md",
          "96.md",
          "97.md",
          "98.md",
          "99.md",
          "100.md",
          "101.md",
          "102.md",
          "103.md",
          "104.md",
          "105.md",
          "106.md",
          "107.md",
          "108.md",
          "109.md",
          "110.md",
          "111.md",
          "112.md",
          "113.md",
          "114.md",
          "115.md",
          "116.md",
          "117.md",
          "118.md",
          "119.md",
          "120.md",
          "121.md",
          "122.md",
          "123.md",
          "124.md",
          "125.md",
          "126.md",
          "127.md",
          "128.md",
          "129.md",
          "130.md",
          "131.md",
          "132.md",
          "133.md",
          "134.md",
          "135.md",
          "136.md",
          "137.md",
          "138.md",
          "139.md",
          "140.md",
          "141.md",
          "142.md",
          "143.md",
          "144.md",
          "145.md",
          "146.md",
          "147.md",
          "148.md",
          "149.md",
          "150.md"
        ],
        "Deuteronomy": [
          "01.md",
          "02.md",
          "03.md",
          "04.md",
          "05.md",
          "06.md",
          "07.md",
          "08.md",
          "09.md",
          "10.md",
          "11.md",
          "12.md",
          "13.md",
          "14.md",
          "15.md",
          "16.md",
          "17.md",
          "18.md",
          "19.md",
          "20.md",
          "21.md",
          "22.md",
          "23.md",
          "24.md",
          "25.md",
          "26.md",
          "27.md",
          "28.md",
          "29.md",
          "30.md",
          "31.md",
          "32.md",
          "33.md",
          "34.md"
        ],
        "Song of Solomon": [
          "01.md",
          "02.md",
          "03.md",
          "04.md",
          "05.md",
          "06.md",
          "07.md",
          "08.md"
        ],
        "Amos": [
          "01.md",
          "02.md",
          "03.md",
          "04.md",
          "05.md",
          "06.md",
          "07.md",
          "08.md",
          "09.md"
        ],
        "Ezekiel": [
          "01.md",
          "02.md",
          "03.md",
          "04.md",
          "05.md",
          "06.md",
          "07.md",
          "08.md",
          "09.md",
          "10.md",
          "11.md",
          "12.md",
          "13.md",
          "14.md",
          "15.md",
          "16.md",
          "17.md",
          "18.md",
          "19.md",
          "20.md",
          "21.md",
          "22.md",
          "23.md",
          "24.md",
          "25.md",
          "26.md",
          "27.md",
          "28.md",
          "29.md",
          "30.md",
          "31.md",
          "32.md",
          "33.md",
          "34.md",
          "35.md",
          "36.md",
          "37.md",
          "38.md",
          "39.md",
          "40.md",
          "41.md",
          "42.md",
          "43.md",
          "44.md",
          "45.md",
          "46.md",
          "47.md",
          "48.md"
        ],
        "Esther": [
          "01.md",
          "02.md",
          "03.md",
          "04.md",
          "05.md",
          "06.md",
          "07.md",
          "08.md",
          "09.md",
          "10.md"
        ],
        "Ezra": [
          "01.md",
          "02.md",
          "03.md",
          "04.md",
          "05.md",
          "06.md",
          "07.md",
          "08.md",
          "09.md",
          "10.md"
        ],
        "Joshua": [
          "01.md",
          "02.md",
          "03.md",
          "04.md",
          "05.md",
          "06.md",
          "07.md",
          "08.md",
          "09.md",
          "10.md",
          "11.md",
          "12.md",
          "13.md",
          "14.md",
          "15.md",
          "16.md",
          "17.md",
          "18.md",
          "19.md",
          "20.md",
          "21.md",
          "22.md",
          "23.md",
          "24.md"
        ],
        "1 Chronicles": [
          "01.md",
          "02.md",
          "03.md",
          "04.md",
          "05.md",
          "06.md",
          "07.md",
          "08.md",
          "09.md",
          "10.md",
          "11.md",
          "12.md",
          "13.md",
          "14.md",
          "15.md",
          "16.md",
          "17.md",
          "18.md",
          "19.md",
          "20.md",
          "21.md",
          "22.md",
          "23.md",
          "24.md",
          "25.md",
          "26.md",
          "27.md",
          "28.md",
          "29.md"
        ],
        "2 Chronicles": [
          "01.md",
          "02.md",
          "03.md",
          "04.md",
          "05.md",
          "06.md",
          "07.md",
          "08.md",
          "09.md",
          "10.md",
          "11.md",
          "12.md",
          "13.md",
          "14.md",
          "15.md",
          "16.md",
          "17.md",
          "18.md",
          "19.md",
          "20.md",
          "21.md",
          "22.md",
          "23.md",
          "24.md",
          "25.md",
          "26.md",
          "27.md",
          "28.md",
          "29.md",
          "30.md",
          "31.md",
          "32.md",
          "33.md",
          "34.md",
          "35.md",
          "36.md"
        ],
        "1 Kings": [
          "01.md",
          "02.md",
          "03.md",
          "04.md",
          "05.md",
          "06.md",
          "07.md",
          "08.md",
          "09.md",
          "10.md",
          "11.md",
          "12.md",
          "13.md",
          "14.md",
          "15.md",
          "16.md",
          "17.md",
          "18.md",
          "19.md",
          "20.md",
          "21.md",
          "22.md"
        ],
        "2 Kings": [
          "01.md",
          "02.md",
          "03.md",
          "04.md",
          "05.md",
          "06.md",
          "07.md",
          "08.md",
          "09.md",
          "10.md",
          "11.md",
          "12.md",
          "13.md",
          "14.md",
          "15.md",
          "16.md",
          "17.md",
          "18.md",
          "19.md",
          "20.md",
          "21.md",
          "22.md",
          "23.md",
          "24.md",
          "25.md"
        ],
        "Jeremiah": [
          "01.md",
          "02.md",
          "03.md",
          "04.md",
          "05.md",
          "06.md",
          "07.md",
          "08.md",
          "09.md",
          "10.md",
          "11.md",
          "12.md",
          "13.md",
          "14.md",
          "15.md",
          "16.md",
          "17.md",
          "18.md",
          "19.md",
          "20.md",
          "21.md",
          "22.md",
          "23.md",
          "24.md",
          "25.md",
          "26.md",
          "27.md",
          "28.md",
          "29.md",
          "30.md",
          "31.md",
          "32.md",
          "33.md",
          "34.md",
          "35.md",
          "36.md",
          "37.md",
          "38.md",
          "39.md",
          "40.md",
          "41.md",
          "42.md",
          "43.md",
          "44.md",
          "45.md",
          "46.md",
          "47.md",
          "48.md",
          "49.md",
          "50.md",
          "51.md",
          "52.md"
        ],
        "Lamentations": [
          "01.md",
          "02.md",
          "03.md",
          "04.md",
          "05.md"
        ],
        "Obadiah": [
          "01.md"
        ],
        "Jonah": [
          "01.md",
          "02.md",
          "03.md",
          "04.md"
        ],
        "Joel": [
          "01.md",
          "02.md",
          "03.md"
        ],
        "Job": [
          "01.md",
          "02.md",
          "03.md",
          "04.md",
          "05.md",
          "06.md",
          "07.md",
          "08.md",
          "09.md",
          "10.md",
          "11.md",
          "12.md",
          "13.md",
          "14.md",
          "15.md",
          "16.md",
          "17.md",
          "18.md",
          "19.md",
          "20.md",
          "21.md",
          "22.md",
          "23.md",
          "24.md",
          "25.md",
          "26.md",
          "27.md",
          "28.md",
          "29.md",
          "30.md",
          "31.md",
          "32.md",
          "33.md",
          "34.md",
          "35.md",
          "36.md",
          "37.md",
          "38.md",
          "39.md",
          "40.md",
          "41.md",
          "42.md"
        ],
        "Isaiah": [
          "01.md",
          "02.md",
          "03.md",
          "04.md",
          "05.md",
          "06.md",
          "07.md",
          "08.md",
          "09.md",
          "10.md",
          "11.md",
          "12.md",
          "13.md",
          "14.md",
          "15.md",
          "16.md",
          "17.md",
          "18.md",
          "19.md",
          "20.md",
          "21.md",
          "22.md",
          "23.md",
          "24.md",
          "25.md",
          "26.md",
          "27.md",
          "28.md",
          "29.md",
          "30.md",
          "31.md",
          "32.md",
          "33.md",
          "34.md",
          "35.md",
          "36.md",
          "37.md",
          "38.md",
          "39.md",
          "40.md",
          "41.md",
          "42.md",
          "43.md",
          "44.md",
          "45.md",
          "46.md",
          "47.md",
          "48.md",
          "49.md",
          "50.md",
          "51.md",
          "52.md",
          "53.md",
          "54.md",
          "55.md",
          "56.md",
          "57.md",
          "58.md",
          "59.md",
          "60.md",
          "61.md",
          "62.md",
          "63.md",
          "64.md",
          "65.md",
          "66.md"
        ],
        "Proverbs": [
          "01.md",
          "02.md",
          "03.md",
          "04.md",
          "05.md",
          "06.md",
          "07.md",
          "08.md",
          "09.md",
          "10.md",
          "11.md",
          "12.md",
          "13.md",
          "14.md",
          "15.md",
          "16.md",
          "17.md",
          "18.md",
          "19.md",
          "20.md",
          "21.md",
          "22.md",
          "23.md",
          "24.md",
          "25.md",
          "26.md",
          "27.md",
          "28.md",
          "29.md",
          "30.md",
          "31.md"
        ],
        "Ecclesiastes": [
          "01.md",
          "02.md",
          "03.md",
          "04.md",
          "05.md",
          "06.md",
          "07.md",
          "08.md",
          "09.md",
          "10.md",
          "11.md",
          "12.md"
        ],
        "Genesis": [
          "01.md",
          "02.md",
          "03.md",
          "04.md",
          "05.md",
          "06.md",
          "07.md",
          "08.md",
          "09.md",
          "10.md",
          "11.md",
          "12.md",
          "13.md",
          "14.md",
          "15.md",
          "16.md",
          "17.md",
          "18.md",
          "19.md",
          "20.md",
          "21.md",
          "22.md",
          "23.md",
          "24.md",
          "25.md",
          "26.md",
          "27.md",
          "28.md",
          "29.md",
          "30.md",
          "31.md",
          "32.md",
          "33.md",
          "34.md",
          "35.md",
          "36.md",
          "37.md",
          "38.md",
          "39.md",
          "40.md",
          "41.md",
          "42.md",
          "43.md",
          "44.md",
          "45.md",
          "46.md",
          "47.md",
          "48.md",
          "49.md",
          "50.md"
        ],
        "Exodus": [
          "01.md",
          "02.md",
          "03.md",
          "04.md",
          "05.md",
          "06.md",
          "07.md",
          "08.md",
          "09.md",
          "10.md",
          "11.md",
          "12.md",
          "13.md",
          "14.md",
          "15.md",
          "16.md",
          "17.md",
          "18.md",
          "19.md",
          "20.md",
          "21.md",
          "22.md",
          "23.md",
          "24.md",
          "25.md",
          "26.md",
          "27.md",
          "28.md",
          "29.md",
          "30.md",
          "31.md",
          "32.md",
          "33.md",
          "34.md",
          "35.md",
          "36.md",
          "37.md",
          "38.md",
          "39.md",
          "40.md"
        ],
        "Habakkuk": [
          "01.md",
          "02.md",
          "03.md"
        ],
        "Haggai": [
          "01.md",
          "02.md"
        ],
        "Hosea": [
          "01.md",
          "02.md",
          "03.md",
          "04.md",
          "05.md",
          "06.md",
          "07.md",
          "08.md",
          "09.md",
          "10.md",
          "11.md",
          "12.md",
          "13.md",
          "14.md"
        ]
      }
    },
    "NKRV": {
      "label": "NKRV (개역개정)",
      "language": "ko",
      "dir": "역본/NKRV",
      "direction": "ltr",
      "bookDirs": {
        "Genesis": "01-창세기",
        "Exodus": "02-출애굽기",
        "Leviticus": "03-레위기",
        "Numbers": "04-민수기",
        "Deuteronomy": "05-신명기",
        "Joshua": "06-여호수아",
        "Judges": "07-사사기",
        "Ruth": "08-룻기",
        "1 Samuel": "09-사무엘상",
        "2 Samuel": "10-사무엘하",
        "1 Kings": "11-열왕기상",
        "2 Kings": "12-열왕기하",
        "1 Chronicles": "13-역대상",
        "2 Chronicles": "14-역대하",
        "Ezra": "15-에스라",
        "Nehemiah": "16-느헤미야",
        "Esther": "17-에스더",
        "Job": "18-욥기",
        "Psalms": "19-시편",
        "Proverbs": "20-잠언",
        "Ecclesiastes": "21-전도서",
        "Song of Solomon": "22-아가",
        "Isaiah": "23-이사야",
        "Jeremiah": "24-예레미야",
        "Lamentations": "25-예레미야애가",
        "Ezekiel": "26-에스겔",
        "Daniel": "27-다니엘",
        "Hosea": "28-호세아",
        "Joel": "29-요엘",
        "Amos": "30-아모스",
        "Obadiah": "31-오바댜",
        "Jonah": "32-요나",
        "Micah": "33-미가",
        "Nahum": "34-나훔",
        "Habakkuk": "35-하박국",
        "Zephaniah": "36-스바냐",
        "Haggai": "37-학개",
        "Zechariah": "38-스가랴",
        "Malachi": "39-말라기"
      },
      "chapterFiles": {
        "Genesis": [
          "001.md",
          "002.md",
          "003.md",
          "004.md",
          "005.md",
          "006.md",
          "007.md",
          "008.md",
          "009.md",
          "010.md",
          "011.md",
          "012.md",
          "013.md",
          "014.md",
          "015.md",
          "016.md",
          "017.md",
          "018.md",
          "019.md",
          "020.md",
          "021.md",
          "022.md",
          "023.md",
          "024.md",
          "025.md",
          "026.md",
          "027.md",
          "028.md",
          "029.md",
          "030.md",
          "031.md",
          "032.md",
          "033.md",
          "034.md",
          "035.md",
          "036.md",
          "037.md",
          "038.md",
          "039.md",
          "040.md",
          "041.md",
          "042.md",
          "043.md",
          "044.md",
          "045.md",
          "046.md",
          "047.md",
          "048.md",
          "049.md",
          "050.md"
        ],
        "Exodus": [
          "001.md",
          "002.md",
          "003.md",
          "004.md",
          "005.md",
          "006.md",
          "007.md",
          "008.md",
          "009.md",
          "010.md",
          "011.md",
          "012.md",
          "013.md",
          "014.md",
          "015.md",
          "016.md",
          "017.md",
          "018.md",
          "019.md",
          "020.md",
          "021.md",
          "022.md",
          "023.md",
          "024.md",
          "025.md",
          "026.md",
          "027.md",
          "028.md",
          "029.md",
          "030.md",
          "031.md",
          "032.md",
          "033.md",
          "034.md",
          "035.md",
          "036.md",
          "037.md",
          "038.md",
          "039.md",
          "040.md"
        ],
        "Leviticus": [
          "001.md",
          "002.md",
          "003.md",
          "004.md",
          "005.md",
          "006.md",
          "007.md",
          "008.md",
          "009.md",
          "010.md",
          "011.md",
          "012.md",
          "013.md",
          "014.md",
          "015.md",
          "016.md",
          "017.md",
          "018.md",
          "019.md",
          "020.md",
          "021.md",
          "022.md",
          "023.md",
          "024.md",
          "025.md",
          "026.md",
          "027.md"
        ],
        "Numbers": [
          "001.md",
          "002.md",
          "003.md",
          "004.md",
          "005.md",
          "006.md",
          "007.md",
          "008.md",
          "009.md",
          "010.md",
          "011.md",
          "012.md",
          "013.md",
          "014.md",
          "015.md",
          "016.md",
          "017.md",
          "018.md",
          "019.md",
          "020.md",
          "021.md",
          "022.md",
          "023.md",
          "024.md",
          "025.md",
          "026.md",
          "027.md",
          "028.md",
          "029.md",
          "030.md",
          "031.md",
          "032.md",
          "033.md",
          "034.md",
          "035.md",
          "036.md"
        ],
        "Deuteronomy": [
          "001.md",
          "002.md",
          "003.md",
          "004.md",
          "005.md",
          "006.md",
          "007.md",
          "008.md",
          "009.md",
          "010.md",
          "011.md",
          "012.md",
          "013.md",
          "014.md",
          "015.md",
          "016.md",
          "017.md",
          "018.md",
          "019.md",
          "020.md",
          "021.md",
          "022.md",
          "023.md",
          "024.md",
          "025.md",
          "026.md",
          "027.md",
          "028.md",
          "029.md",
          "030.md",
          "031.md",
          "032.md",
          "033.md",
          "034.md"
        ],
        "Joshua": [
          "001.md",
          "002.md",
          "003.md",
          "004.md",
          "005.md",
          "006.md",
          "007.md",
          "008.md",
          "009.md",
          "010.md",
          "011.md",
          "012.md",
          "013.md",
          "014.md",
          "015.md",
          "016.md",
          "017.md",
          "018.md",
          "019.md",
          "020.md",
          "021.md",
          "022.md",
          "023.md",
          "024.md"
        ],
        "Judges": [
          "001.md",
          "002.md",
          "003.md",
          "004.md",
          "005.md",
          "006.md",
          "007.md",
          "008.md",
          "009.md",
          "010.md",
          "011.md",
          "012.md",
          "013.md",
          "014.md",
          "015.md",
          "016.md",
          "017.md",
          "018.md",
          "019.md",
          "020.md",
          "021.md"
        ],
        "Ruth": [
          "001.md",
          "002.md",
          "003.md",
          "004.md"
        ],
        "1 Samuel": [
          "001.md",
          "002.md",
          "003.md",
          "004.md",
          "005.md",
          "006.md",
          "007.md",
          "008.md",
          "009.md",
          "010.md",
          "011.md",
          "012.md",
          "013.md",
          "014.md",
          "015.md",
          "016.md",
          "017.md",
          "018.md",
          "019.md",
          "020.md",
          "021.md",
          "022.md",
          "023.md",
          "024.md",
          "025.md",
          "026.md",
          "027.md",
          "028.md",
          "029.md",
          "030.md",
          "031.md"
        ],
        "2 Samuel": [
          "001.md",
          "002.md",
          "003.md",
          "004.md",
          "005.md",
          "006.md",
          "007.md",
          "008.md",
          "009.md",
          "010.md",
          "011.md",
          "012.md",
          "013.md",
          "014.md",
          "015.md",
          "016.md",
          "017.md",
          "018.md",
          "019.md",
          "020.md",
          "021.md",
          "022.md",
          "023.md",
          "024.md"
        ],
        "1 Kings": [
          "001.md",
          "002.md",
          "003.md",
          "004.md",
          "005.md",
          "006.md",
          "007.md",
          "008.md",
          "009.md",
          "010.md",
          "011.md",
          "012.md",
          "013.md",
          "014.md",
          "015.md",
          "016.md",
          "017.md",
          "018.md",
          "019.md",
          "020.md",
          "021.md",
          "022.md"
        ],
        "2 Kings": [
          "001.md",
          "002.md",
          "003.md",
          "004.md",
          "005.md",
          "006.md",
          "007.md",
          "008.md",
          "009.md",
          "010.md",
          "011.md",
          "012.md",
          "013.md",
          "014.md",
          "015.md",
          "016.md",
          "017.md",
          "018.md",
          "019.md",
          "020.md",
          "021.md",
          "022.md",
          "023.md",
          "024.md",
          "025.md"
        ],
        "1 Chronicles": [
          "001.md",
          "002.md",
          "003.md",
          "004.md",
          "005.md",
          "006.md",
          "007.md",
          "008.md",
          "009.md",
          "010.md",
          "011.md",
          "012.md",
          "013.md",
          "014.md",
          "015.md",
          "016.md",
          "017.md",
          "018.md",
          "019.md",
          "020.md",
          "021.md",
          "022.md",
          "023.md",
          "024.md",
          "025.md",
          "026.md",
          "027.md",
          "028.md",
          "029.md"
        ],
        "2 Chronicles": [
          "001.md",
          "002.md",
          "003.md",
          "004.md",
          "005.md",
          "006.md",
          "007.md",
          "008.md",
          "009.md",
          "010.md",
          "011.md",
          "012.md",
          "013.md",
          "014.md",
          "015.md",
          "016.md",
          "017.md",
          "018.md",
          "019.md",
          "020.md",
          "021.md",
          "022.md",
          "023.md",
          "024.md",
          "025.md",
          "026.md",
          "027.md",
          "028.md",
          "029.md",
          "030.md",
          "031.md",
          "032.md",
          "033.md",
          "034.md",
          "035.md",
          "036.md"
        ],
        "Ezra": [
          "001.md",
          "002.md",
          "003.md",
          "004.md",
          "005.md",
          "006.md",
          "007.md",
          "008.md",
          "009.md",
          "010.md"
        ],
        "Nehemiah": [
          "001.md",
          "002.md",
          "003.md",
          "004.md",
          "005.md",
          "006.md",
          "007.md",
          "008.md",
          "009.md",
          "010.md",
          "011.md",
          "012.md",
          "013.md"
        ],
        "Esther": [
          "001.md",
          "002.md",
          "003.md",
          "004.md",
          "005.md",
          "006.md",
          "007.md",
          "008.md",
          "009.md",
          "010.md"
        ],
        "Job": [
          "001.md",
          "002.md",
          "003.md",
          "004.md",
          "005.md",
          "006.md",
          "007.md",
          "008.md",
          "009.md",
          "010.md",
          "011.md",
          "012.md",
          "013.md",
          "014.md",
          "015.md",
          "016.md",
          "017.md",
          "018.md",
          "019.md",
          "020.md",
          "021.md",
          "022.md",
          "023.md",
          "024.md",
          "025.md",
          "026.md",
          "027.md",
          "028.md",
          "029.md",
          "030.md",
          "031.md",
          "032.md",
          "033.md",
          "034.md",
          "035.md",
          "036.md",
          "037.md",
          "038.md",
          "039.md",
          "040.md",
          "041.md",
          "042.md"
        ],
        "Psalms": [
          "001.md",
          "002.md",
          "003.md",
          "004.md",
          "005.md",
          "006.md",
          "007.md",
          "008.md",
          "009.md",
          "010.md",
          "011.md",
          "012.md",
          "013.md",
          "014.md",
          "015.md",
          "016.md",
          "017.md",
          "018.md",
          "019.md",
          "020.md",
          "021.md",
          "022.md",
          "023.md",
          "024.md",
          "025.md",
          "026.md",
          "027.md",
          "028.md",
          "029.md",
          "030.md",
          "031.md",
          "032.md",
          "033.md",
          "034.md",
          "035.md",
          "036.md",
          "037.md",
          "038.md",
          "039.md",
          "040.md",
          "041.md",
          "042.md",
          "043.md",
          "044.md",
          "045.md",
          "046.md",
          "047.md",
          "048.md",
          "049.md",
          "050.md",
          "051.md",
          "052.md",
          "053.md",
          "054.md",
          "055.md",
          "056.md",
          "057.md",
          "058.md",
          "059.md",
          "060.md",
          "061.md",
          "062.md",
          "063.md",
          "064.md",
          "065.md",
          "066.md",
          "067.md",
          "068.md",
          "069.md",
          "070.md",
          "071.md",
          "072.md",
          "073.md",
          "074.md",
          "075.md",
          "076.md",
          "077.md",
          "078.md",
          "079.md",
          "080.md",
          "081.md",
          "082.md",
          "083.md",
          "084.md",
          "085.md",
          "086.md",
          "087.md",
          "088.md",
          "089.md",
          "090.md",
          "091.md",
          "092.md",
          "093.md",
          "094.md",
          "095.md",
          "096.md",
          "097.md",
          "098.md",
          "099.md",
          "100.md",
          "101.md",
          "102.md",
          "103.md",
          "104.md",
          "105.md",
          "106.md",
          "107.md",
          "108.md",
          "109.md",
          "110.md",
          "111.md",
          "112.md",
          "113.md",
          "114.md",
          "115.md",
          "116.md",
          "117.md",
          "118.md",
          "119.md",
          "120.md",
          "121.md",
          "122.md",
          "123.md",
          "124.md",
          "125.md",
          "126.md",
          "127.md",
          "128.md",
          "129.md",
          "130.md",
          "131.md",
          "132.md",
          "133.md",
          "134.md",
          "135.md",
          "136.md",
          "137.md",
          "138.md",
          "139.md",
          "140.md",
          "141.md",
          "142.md",
          "143.md",
          "144.md",
          "145.md",
          "146.md",
          "147.md",
          "148.md",
          "149.md",
          "150.md"
        ],
        "Proverbs": [
          "001.md",
          "002.md",
          "003.md",
          "004.md",
          "005.md",
          "006.md",
          "007.md",
          "008.md",
          "009.md",
          "010.md",
          "011.md",
          "012.md",
          "013.md",
          "014.md",
          "015.md",
          "016.md",
          "017.md",
          "018.md",
          "019.md",
          "020.md",
          "021.md",
          "022.md",
          "023.md",
          "024.md",
          "025.md",
          "026.md",
          "027.md",
          "028.md",
          "029.md",
          "030.md",
          "031.md"
        ],
        "Ecclesiastes": [
          "001.md",
          "002.md",
          "003.md",
          "004.md",
          "005.md",
          "006.md",
          "007.md",
          "008.md",
          "009.md",
          "010.md",
          "011.md",
          "012.md"
        ],
        "Song of Solomon": [
          "001.md",
          "002.md",
          "003.md",
          "004.md",
          "005.md",
          "006.md",
          "007.md",
          "008.md"
        ],
        "Isaiah": [
          "001.md",
          "002.md",
          "003.md",
          "004.md",
          "005.md",
          "006.md",
          "007.md",
          "008.md",
          "009.md",
          "010.md",
          "011.md",
          "012.md",
          "013.md",
          "014.md",
          "015.md",
          "016.md",
          "017.md",
          "018.md",
          "019.md",
          "020.md",
          "021.md",
          "022.md",
          "023.md",
          "024.md",
          "025.md",
          "026.md",
          "027.md",
          "028.md",
          "029.md",
          "030.md",
          "031.md",
          "032.md",
          "033.md",
          "034.md",
          "035.md",
          "036.md",
          "037.md",
          "038.md",
          "039.md",
          "040.md",
          "041.md",
          "042.md",
          "043.md",
          "044.md",
          "045.md",
          "046.md",
          "047.md",
          "048.md",
          "049.md",
          "050.md",
          "051.md",
          "052.md",
          "053.md",
          "054.md",
          "055.md",
          "056.md",
          "057.md",
          "058.md",
          "059.md",
          "060.md",
          "061.md",
          "062.md",
          "063.md",
          "064.md",
          "065.md",
          "066.md"
        ],
        "Jeremiah": [
          "001.md",
          "002.md",
          "003.md",
          "004.md",
          "005.md",
          "006.md",
          "007.md",
          "008.md",
          "009.md",
          "010.md",
          "011.md",
          "012.md",
          "013.md",
          "014.md",
          "015.md",
          "016.md",
          "017.md",
          "018.md",
          "019.md",
          "020.md",
          "021.md",
          "022.md",
          "023.md",
          "024.md",
          "025.md",
          "026.md",
          "027.md",
          "028.md",
          "029.md",
          "030.md",
          "031.md",
          "032.md",
          "033.md",
          "034.md",
          "035.md",
          "036.md",
          "037.md",
          "038.md",
          "039.md",
          "040.md",
          "041.md",
          "042.md",
          "043.md",
          "044.md",
          "045.md",
          "046.md",
          "047.md",
          "048.md",
          "049.md",
          "050.md",
          "051.md",
          "052.md"
        ],
        "Lamentations": [
          "001.md",
          "002.md",
          "003.md",
          "004.md",
          "005.md"
        ],
        "Ezekiel": [
          "001.md",
          "002.md",
          "003.md",
          "004.md",
          "005.md",
          "006.md",
          "007.md",
          "008.md",
          "009.md",
          "010.md",
          "011.md",
          "012.md",
          "013.md",
          "014.md",
          "015.md",
          "016.md",
          "017.md",
          "018.md",
          "019.md",
          "020.md",
          "021.md",
          "022.md",
          "023.md",
          "024.md",
          "025.md",
          "026.md",
          "027.md",
          "028.md",
          "029.md",
          "030.md",
          "031.md",
          "032.md",
          "033.md",
          "034.md",
          "035.md",
          "036.md",
          "037.md",
          "038.md",
          "039.md",
          "040.md",
          "041.md",
          "042.md",
          "043.md",
          "044.md",
          "045.md",
          "046.md",
          "047.md",
          "048.md"
        ],
        "Daniel": [
          "001.md",
          "002.md",
          "003.md",
          "004.md",
          "005.md",
          "006.md",
          "007.md",
          "008.md",
          "009.md",
          "010.md",
          "011.md",
          "012.md"
        ],
        "Hosea": [
          "001.md",
          "002.md",
          "003.md",
          "004.md",
          "005.md",
          "006.md",
          "007.md",
          "008.md",
          "009.md",
          "010.md",
          "011.md",
          "012.md",
          "013.md",
          "014.md"
        ],
        "Joel": [
          "001.md",
          "002.md",
          "003.md"
        ],
        "Amos": [
          "001.md",
          "002.md",
          "003.md",
          "004.md",
          "005.md",
          "006.md",
          "007.md",
          "008.md",
          "009.md"
        ],
        "Obadiah": [
          "001.md"
        ],
        "Jonah": [
          "001.md",
          "002.md",
          "003.md",
          "004.md"
        ],
        "Micah": [
          "001.md",
          "002.md",
          "003.md",
          "004.md",
          "005.md",
          "006.md",
          "007.md"
        ],
        "Nahum": [
          "001.md",
          "002.md",
          "003.md"
        ],
        "Habakkuk": [
          "001.md",
          "002.md",
          "003.md"
        ],
        "Zephaniah": [
          "001.md",
          "002.md",
          "003.md"
        ],
        "Haggai": [
          "001.md",
          "002.md"
        ],
        "Zechariah": [
          "001.md",
          "002.md",
          "003.md",
          "004.md",
          "005.md",
          "006.md",
          "007.md",
          "008.md",
          "009.md",
          "010.md",
          "011.md",
          "012.md",
          "013.md",
          "014.md"
        ],
        "Malachi": [
          "001.md",
          "002.md",
          "003.md",
          "004.md"
        ]
      }
    }
  },
  "availability": {
    "Genesis": [
      "BHS",
      "KNT",
      "NKRV"
    ],
    "Exodus": [
      "BHS",
      "KNT",
      "NKRV"
    ],
    "Leviticus": [
      "BHS",
      "KNT",
      "NKRV"
    ],
    "Numbers": [
      "BHS",
      "KNT",
      "NKRV"
    ],
    "Deuteronomy": [
      "BHS",
      "KNT",
      "NKRV"
    ],
    "Joshua": [
      "BHS",
      "KNT",
      "NKRV"
    ],
    "Judges": [
      "BHS",
      "KNT",
      "NKRV"
    ],
    "Ruth": [
      "BHS",
      "KNT",
      "NKRV"
    ],
    "1 Samuel": [
      "BHS",
      "KNT",
      "NKRV"
    ],
    "2 Samuel": [
      "BHS",
      "KNT",
      "NKRV"
    ],
    "1 Kings": [
      "BHS",
      "KNT",
      "NKRV"
    ],
    "2 Kings": [
      "BHS",
      "KNT",
      "NKRV"
    ],
    "1 Chronicles": [
      "BHS",
      "KNT",
      "NKRV"
    ],
    "2 Chronicles": [
      "BHS",
      "KNT",
      "NKRV"
    ],
    "Ezra": [
      "BHS",
      "KNT",
      "NKRV"
    ],
    "Nehemiah": [
      "BHS",
      "KNT",
      "NKRV"
    ],
    "Esther": [
      "BHS",
      "KNT",
      "NKRV"
    ],
    "Job": [
      "BHS",
      "KNT",
      "NKRV"
    ],
    "Psalms": [
      "BHS",
      "KNT",
      "NKRV"
    ],
    "Proverbs": [
      "BHS",
      "KNT",
      "NKRV"
    ],
    "Ecclesiastes": [
      "BHS",
      "KNT",
      "NKRV"
    ],
    "Song of Solomon": [
      "BHS",
      "KNT",
      "NKRV"
    ],
    "Isaiah": [
      "BHS",
      "KNT",
      "NKRV"
    ],
    "Jeremiah": [
      "BHS",
      "KNT",
      "NKRV"
    ],
    "Lamentations": [
      "BHS",
      "KNT",
      "NKRV"
    ],
    "Ezekiel": [
      "BHS",
      "KNT",
      "NKRV"
    ],
    "Daniel": [
      "BHS",
      "KNT",
      "NKRV"
    ],
    "Hosea": [
      "BHS",
      "KNT",
      "NKRV"
    ],
    "Joel": [
      "BHS",
      "KNT",
      "NKRV"
    ],
    "Amos": [
      "BHS",
      "KNT",
      "NKRV"
    ],
    "Obadiah": [
      "BHS",
      "KNT",
      "NKRV"
    ],
    "Jonah": [
      "BHS",
      "KNT",
      "NKRV"
    ],
    "Micah": [
      "BHS",
      "KNT",
      "NKRV"
    ],
    "Nahum": [
      "BHS",
      "KNT",
      "NKRV"
    ],
    "Habakkuk": [
      "BHS",
      "KNT",
      "NKRV"
    ],
    "Zephaniah": [
      "BHS",
      "KNT",
      "NKRV"
    ],
    "Haggai": [
      "BHS",
      "KNT",
      "NKRV"
    ],
    "Zechariah": [
      "BHS",
      "KNT",
      "NKRV"
    ],
    "Malachi": [
      "BHS",
      "KNT",
      "NKRV"
    ]
  }
}